pyqrack/__init__.py
pyqrack/neuron_activation_fn.py
pyqrack/pauli.py
pyqrack/qrack_ace_backend.py
pyqrack/qrack_circuit.py
pyqrack/qrack_neuron.py
pyqrack/qrack_neuron_torch_layer.py
pyqrack/qrack_simulator.py
pyqrack/qrack_stabilizer.py
pyqrack/quimb_circuit_type.py
pyqrack/qrack_system/__init__.py
pyqrack/qrack_system/qrack_system.py
pyqrack/qrack_system/qrack_cl_precompile/qrack_cl_precompile
pyqrack/qrack_system/qrack_lib/libqrack_pinvoke.so
pyqrack/qrack_system/qrack_lib/libqrack_pinvoke.so.10.0.2
pyqrack/stats/__init__.py
pyqrack/stats/load_quantized_data.py
pyqrack/stats/quantize_by_range.py
pyqrack_complex128-1.83.0.dist-info/LICENSE
pyqrack_complex128-1.83.0.dist-info/METADATA
pyqrack_complex128-1.83.0.dist-info/WHEEL
pyqrack_complex128-1.83.0.dist-info/top_level.txt
pyqrack_complex128-1.83.0.dist-info/RECORD
